pykap/__init__.py
pykap/bist_company_list.py
pykap/get_bist_companies.py
pykap/get_general_info.py
pykap/bist/BISTCompany.py
pykap/bist/__init__.py
pykap/data/bist_companies_general.json
pykap/investment_funds/__init__.py
pykap-0.0.2.3.dist-info/LICENSE
pykap-0.0.2.3.dist-info/METADATA
pykap-0.0.2.3.dist-info/WHEEL
pykap-0.0.2.3.dist-info/top_level.txt
pykap-0.0.2.3.dist-info/RECORD
