Metadata-Version: 2.1
Name: pykap
Version: 0.0.2.3
Summary: KAP (Public Disclosure Platform) Documentation Wrapper for Capital Markets Board of Turkey and Borsa Istanbul Public Disclosures
Home-page: https://github.com/cemsinano/pykap
Author: Cem Sinan Ozturk
Author-email: cemsinanozturk@gmail.com
Project-URL: Bug Tracker, https://github.com/cemsinano/pykap/issues
Classifier: Programming Language :: Python :: 3
Classifier: License :: OSI Approved :: MIT License
Classifier: Operating System :: OS Independent
Requires-Python: >=3.6
License-File: LICENSE
Requires-Dist: bs4
Requires-Dist: pandas
Requires-Dist: requests
Requires-Dist: regex
Requires-Dist: html5lib
